bife/cli.py
bife/config.py
bife/config.template
bife/structs/default/.env.template
bife/structs/default/app.py
bife/structs/default/config.py
bife/structs/default/general/controller.template
bife/structs/default/general/models.template
bife/structs/default/general/repository.template
bife/structs/default/general/schemas.template
bife/structs/default/generate.py
bife/structs/default/libs/api/__init__.py
bife/structs/default/libs/api/api_handler.py
bife/structs/default/libs/bootstrap/bootstrap.py
bife/structs/default/libs/database/__init__.py
bife/structs/default/libs/database/base.py
bife/structs/default/libs/database/database_handler.py
bife/structs/default/libs/security/__init__.py
bife/structs/default/libs/security/security.template
bife/structs/default/main.py
bife/structs/default/modules/user/controller.py
bife/structs/default/modules/user/events.py
bife/structs/default/modules/user/ext.py
bife/structs/default/modules/user/models.py
bife/structs/default/modules/user/repository.py
bife/structs/default/modules/user/schemas.py
bife/structs/default/modules/user/service.py
bife/structs/default/utils/__init__.py
bife/structs/default/utils/email_validator.py
bife-0.1.19.dist-info/METADATA
bife-0.1.19.dist-info/WHEEL
bife-0.1.19.dist-info/entry_points.txt
bife-0.1.19.dist-info/RECORD
